citrine/__init__.py
citrine/__version__.py
citrine/_session.py
citrine/citrine.py
citrine/exceptions.py
citrine/_rest/__init__.py
citrine/_rest/admin_collection.py
citrine/_rest/ai_resource_metadata.py
citrine/_rest/asynchronous_object.py
citrine/_rest/collection.py
citrine/_rest/engine_resource.py
citrine/_rest/pageable.py
citrine/_rest/paginator.py
citrine/_rest/resource.py
citrine/_serialization/__init__.py
citrine/_serialization/include_parent_properties.py
citrine/_serialization/polymorphic_serializable.py
citrine/_serialization/properties.py
citrine/_serialization/serializable.py
citrine/_utils/__init__.py
citrine/_utils/batcher.py
citrine/_utils/functions.py
citrine/_utils/template_util.py
citrine/gemd_queries/__init__.py
citrine/gemd_queries/criteria.py
citrine/gemd_queries/filter.py
citrine/gemd_queries/gemd_query.py
citrine/gemtables/__init__.py
citrine/gemtables/columns.py
citrine/gemtables/rows.py
citrine/gemtables/variables.py
citrine/informatics/__init__.py
citrine/informatics/data_sources.py
citrine/informatics/descriptors.py
citrine/informatics/design_candidate.py
citrine/informatics/dimensions.py
citrine/informatics/experiment_values.py
citrine/informatics/feature_effects.py
citrine/informatics/generative_design.py
citrine/informatics/objectives.py
citrine/informatics/predict_request.py
citrine/informatics/predictor_evaluation_metrics.py
citrine/informatics/predictor_evaluation_result.py
citrine/informatics/predictor_evaluator.py
citrine/informatics/reports.py
citrine/informatics/scores.py
citrine/informatics/catalyst/__init__.py
citrine/informatics/catalyst/assistant.py
citrine/informatics/catalyst/insights.py
citrine/informatics/catalyst/language_model.py
citrine/informatics/constraints/__init__.py
citrine/informatics/constraints/categorical_constraint.py
citrine/informatics/constraints/constraint.py
citrine/informatics/constraints/ingredient_count_constraint.py
citrine/informatics/constraints/ingredient_fraction_constraint.py
citrine-3.26.0.dist-info/LICENSE
citrine-3.26.0.dist-info/METADATA
citrine-3.26.0.dist-info/WHEEL
citrine-3.26.0.dist-info/top_level.txt
citrine-3.26.0.dist-info/RECORD
