Metadata-Version: 2.1
Name: citrine
Version: 3.26.0
Summary: Python library for the Citrine Platform
Home-page: http://github.com/CitrineInformatics/citrine-python
Author: Citrine Informatics
Classifier: Programming Language :: Python :: 3
Classifier: Programming Language :: Python :: 3.8
Classifier: Programming Language :: Python :: 3.9
Classifier: Programming Language :: Python :: 3.10
Classifier: Programming Language :: Python :: 3.11
Classifier: Programming Language :: Python :: 3.12
Classifier: Programming Language :: Python :: 3.13
Requires-Python: >=3.8
License-File: LICENSE
Requires-Dist: arrow <2,>=1.0.0
Requires-Dist: boto3 <2,>=1.34.35
Requires-Dist: deprecation <3,>=2.1.0
Requires-Dist: gemd <3,>=2.1.9
Requires-Dist: pyjwt <3,>=2
Requires-Dist: requests <3,>=2.32.2
Requires-Dist: tqdm <5,>=4.27.0
Requires-Dist: urllib3 <3,>=1.26.18 ; python_version < "3.10"
Requires-Dist: urllib3 <3,>=2.5.0 ; python_version >= "3.10"
Provides-Extra: tests
Requires-Dist: factory-boy <4,>=3.3.0 ; extra == 'tests'
Requires-Dist: mock <6,>=5.1.0 ; extra == 'tests'
Requires-Dist: pandas <3,>=2.0.3 ; extra == 'tests'
Requires-Dist: pytest <9,>=8.0.0 ; extra == 'tests'
Requires-Dist: requests-mock <2,>=1.11.0 ; extra == 'tests'
